{
  "main": {
    "id": "67895ff039e9e009",
    "type": "split",
    "children": [
      {
        "id": "b334f35b6156e395",
        "type": "split",
        "children": [
          {
            "id": "434fe4065303d88b",
            "type": "tabs",
            "children": [
              {
                "id": "4ee2fd852dd0f820",
                "type": "leaf",
                "state": {
                  "type": "markdown",
                  "state": {
                    "file": "Fundamentos/1 - Tipos de dados/Tipos de dados.md",
                    "mode": "source",
                    "source": false
                  }
                }
              }
            ]
          },
          {
            "id": "1fac6650fa5f00d0",
            "type": "split",
            "children": [
              {
                "id": "8e711fb3f5b22ae9",
                "type": "tabs",
                "children": [
                  {
                    "id": "bb6001bc97bc1f01",
                    "type": "leaf",
                    "state": {
                      "type": "graph",
                      "state": {}
                    }
                  }
                ]
              },
              {
                "id": "02383896b2f337d6",
                "type": "tabs",
                "children": [
                  {
                    "id": "f90b1c933ee10d8e",
                    "type": "leaf",
                    "state": {
                      "type": "git-view",
                      "state": {}
                    }
                  }
                ]
              }
            ],
            "direction": "horizontal"
          }
        ],
        "direction": "vertical"
      }
    ],
    "direction": "vertical"
  },
  "left": {
    "id": "dcf85736826e8320",
    "type": "split",
    "children": [
      {
        "id": "42a8b8fd489549b8",
        "type": "tabs",
        "children": [
          {
            "id": "bd612f8143917d0d",
            "type": "leaf",
            "state": {
              "type": "file-explorer",
              "state": {
                "sortOrder": "alphabetical"
              }
            }
          },
          {
            "id": "0b262bdd1e3e37f0",
            "type": "leaf",
            "state": {
              "type": "search",
              "state": {
                "query": "",
                "matchingCase": false,
                "explainSearch": false,
                "collapseAll": false,
                "extraContext": false,
                "sortOrder": "alphabetical"
              }
            }
          },
          {
            "id": "13a0c506859dbb8d",
            "type": "leaf",
            "state": {
              "type": "bookmarks",
              "state": {}
            }
          }
        ]
      }
    ],
    "direction": "horizontal",
    "width": 305
  },
  "right": {
    "id": "245760c334de7a0b",
    "type": "split",
    "children": [
      {
        "id": "a0adc2429e63ef62",
        "type": "tabs",
        "children": [
          {
            "id": "691faf1d70f857d0",
            "type": "leaf",
            "state": {
              "type": "backlink",
              "state": {
                "file": "Fundamentos/1 - Tipos de dados/Tipos de dados.md",
                "collapseAll": false,
                "extraContext": false,
                "sortOrder": "alphabetical",
                "showSearch": false,
                "searchQuery": "",
                "backlinkCollapsed": false,
                "unlinkedCollapsed": true
              }
            }
          },
          {
            "id": "d5b0a09582a92741",
            "type": "leaf",
            "state": {
              "type": "outgoing-link",
              "state": {
                "file": "Fundamentos/1 - Tipos de dados/Tipos de dados.md",
                "linksCollapsed": false,
                "unlinkedCollapsed": true
              }
            }
          },
          {
            "id": "0382db9bcfbcb900",
            "type": "leaf",
            "state": {
              "type": "tag",
              "state": {
                "sortOrder": "frequency",
                "useHierarchy": true
              }
            }
          },
          {
            "id": "476c430dff6e16f7",
            "type": "leaf",
            "state": {
              "type": "outline",
              "state": {
                "file": "Fundamentos/1 - Tipos de dados/Tipos de dados.md"
              }
            }
          }
        ],
        "currentTab": 3
      }
    ],
    "direction": "horizontal",
    "width": 200,
    "collapsed": true
  },
  "left-ribbon": {
    "hiddenItems": {
      "switcher:Abrir a troca rápida": false,
      "graph:Abrir visualização em gráfico": false,
      "canvas:Criar novo canvas": false,
      "daily-notes:Abrir a nota de hoje": false,
      "templates:Inserir modelo": false,
      "command-palette:Abrir paleta de comandos": false,
      "homepage:Open homepage": false,
      "terminal:Open terminal": false
    }
  },
  "active": "4ee2fd852dd0f820",
  "lastOpenFiles": [
    "Fundamentos/1 - Tipos de dados/Primitivos.md",
    "Imagens/Csharp_Dev_Kit.png",
    "Fundamentos/2 - Operadores/Comparação.md",
    "Imagens",
    "Fundamentos/2 - Operadores/Operadores.md",
    "Fundamentos/2 - Operadores/Atribuicao.md",
    "Fundamentos/2 - Operadores/Aritméticos.md",
    "Home.md",
    "Fundamentos/Fundamentos.md",
    "Fundamentos/1 - Tipos de dados/Tipos de dados.md",
    "Fundamentos/1 - Tipos de dados/Conversões.md",
    "Fundamentos/5 - Funções e Métodos",
    "Fundamentos/4 - Laços de Repetição",
    "Fundamentos/3 - Estruturas Condicionais",
    "Fundamentos/2 - Operadores",
    "Fundamentos/1 - Tipos de dados",
    "Fundamentos"
  ]
}